Metadata-Version: 2.1
Name: pypot
Version: 5.0.2
Summary: Python 3 Library for Robot Control
Home-page: https://github.com/poppy-project/pypot
Author: See https://github.com/poppy-project/pypot/graphs/contributors
Author-email: dev@poppy-station.org
License: GNU GENERAL PUBLIC LICENSE Version 3
Platform: UNKNOWN
Classifier: Programming Language :: Python :: 3
Classifier: Topic :: Scientific/Engineering
Provides-Extra: doc
Provides-Extra: zmq-server
Provides-Extra: remote-robot
Provides-Extra: camera
Provides-Extra: tests
License-File: LICENSE.txt
